shepherd_core/__init__.py
shepherd_core/calibration_hw_def.py
shepherd_core/commons.py
shepherd_core/config.py
shepherd_core/logger.py
shepherd_core/reader.py
shepherd_core/version.py
shepherd_core/writer.py
shepherd_core/data_models/__init__.py
shepherd_core/data_models/readme.md
shepherd_core/data_models/virtual_source_doc.txt
shepherd_core/data_models/base/__init__.py
shepherd_core/data_models/base/cal_measurement.py
shepherd_core/data_models/base/calibration.py
shepherd_core/data_models/base/content.py
shepherd_core/data_models/base/shepherd.py
shepherd_core/data_models/base/timezone.py
shepherd_core/data_models/base/wrapper.py
shepherd_core/data_models/content/__init__.py
shepherd_core/data_models/content/_external_fixtures.yaml
shepherd_core/data_models/content/energy_environment.py
shepherd_core/data_models/content/energy_environment_fixture.yaml
shepherd_core/data_models/content/firmware.py
shepherd_core/data_models/content/firmware_datatype.py
shepherd_core/data_models/content/virtual_harvester.py
shepherd_core/data_models/content/virtual_harvester_fixture.yaml
shepherd_core/data_models/content/virtual_source.py
shepherd_core/data_models/content/virtual_source_fixture.yaml
shepherd_core/data_models/experiment/__init__.py
shepherd_core/data_models/experiment/experiment.py
shepherd_core/data_models/experiment/observer_features.py
shepherd_core/data_models/experiment/target_config.py
shepherd_core/data_models/task/__init__.py
shepherd_core/data_models/task/emulation.py
shepherd_core/data_models/task/firmware_mod.py
shepherd_core/data_models/task/harvest.py
shepherd_core/data_models/task/helper_paths.py
shepherd_core/data_models/task/observer_tasks.py
shepherd_core/data_models/task/programming.py
shepherd_core/data_models/task/testbed_tasks.py
shepherd_core/data_models/testbed/__init__.py
shepherd_core/data_models/testbed/cape.py
shepherd_core/data_models/testbed/cape_fixture.yaml
shepherd_core/data_models/testbed/gpio.py
shepherd_core-2025.8.1.dist-info/METADATA
shepherd_core-2025.8.1.dist-info/WHEEL
shepherd_core-2025.8.1.dist-info/top_level.txt
shepherd_core-2025.8.1.dist-info/zip-safe
shepherd_core-2025.8.1.dist-info/RECORD
