Metadata-Version: 2.4
Name: shepherd_core
Version: 2025.8.1
Summary: Programming- and CLI-Interface for the h5-dataformat of the Shepherd-Testbed
Author-email: Ingmar Splitt <ingmar.splitt@tu-dresden.de>
Maintainer-email: Ingmar Splitt <ingmar.splitt@tu-dresden.de>
Project-URL: Documentation, https://github.com/nes-lab/shepherd-tools/blob/main/README.md
Project-URL: Issues, https://github.com/nes-lab/shepherd-tools/issues
Project-URL: Source, https://pypi.org/project/shepherd-core/
Keywords: testbed,beaglebone,pru,batteryless,energyharvesting,solar
Platform: unix
Platform: linux
Platform: osx
Platform: cygwin
Platform: win32
Platform: win64
Classifier: Development Status :: 5 - Production/Stable
Classifier: Intended Audience :: Developers
Classifier: Intended Audience :: Information Technology
Classifier: Intended Audience :: Science/Research
Classifier: Programming Language :: Python :: 3.10
Classifier: Programming Language :: Python :: 3.11
Classifier: Programming Language :: Python :: 3.12
Classifier: Programming Language :: Python :: 3.13
Classifier: License :: OSI Approved :: MIT License
Classifier: Operating System :: OS Independent
Classifier: Natural Language :: English
Requires-Python: >=3.10
Requires-Dist: h5py
Requires-Dist: numpy
Requires-Dist: pyYAML
Requires-Dist: chromalog
Requires-Dist: pydantic[email]>2.0.0
Requires-Dist: tqdm
Requires-Dist: intelhex
Requires-Dist: requests
Requires-Dist: pyelftools
Requires-Dist: zstandard
Requires-Dist: typing-extensions
Provides-Extra: elf
Requires-Dist: pwntools-elf-only; extra == "elf"
Provides-Extra: inventory
Requires-Dist: psutil; extra == "inventory"
Provides-Extra: dev
Requires-Dist: types-PyYAML; extra == "dev"
Provides-Extra: test
Requires-Dist: pytest; extra == "test"
Requires-Dist: coverage; extra == "test"
Provides-Extra: all
Requires-Dist: shepherd-core[dev,elf,inventory,test]; extra == "all"
